ultrachic/UltraChic.py
ultrachic/UltraDefines.py
ultrachic/UltraPackets.py
ultrachic/UltraVersion.py
ultrachic/__init__.py
ultrachic/__main__.py
ultrachic-1.1.0.dist-info/METADATA
ultrachic-1.1.0.dist-info/WHEEL
ultrachic-1.1.0.dist-info/entry_points.txt
ultrachic-1.1.0.dist-info/top_level.txt
ultrachic-1.1.0.dist-info/RECORD
